[
  {
    "full_name": "simonw/sqlite-utils",
    "stargazers_count": 1477,
    "open_issues_count": 97,
    "forks_count": 102
  },
  {
    "full_name": "freeCodeCamp/devdocs",
    "stargazers_count": 33722,
    "open_issues_count": 184,
    "forks_count": 2242
  },
  {
    "full_name": "henrik-ch/open-sauced-goals",
    "stargazers_count": 0,
    "open_issues_count": 6,
    "forks_count": 0
  },
  {
    "full_name": "saulpw/visidata",
    "stargazers_count": 7364,
    "open_issues_count": 81,
    "forks_count": 270
  },
  {
    "full_name": "nix-community/poetry2nix",
    "stargazers_count": 709,
    "open_issues_count": 174,
    "forks_count": 374
  },
  {
    "full_name": "open-sauced/open-sauced",
    "stargazers_count": 916,
    "open_issues_count": 0,
    "forks_count": 859
  }
]