[
  {
    "full_name": "simonw/sqlite-utils",
    "stargazers_count": 1087,
    "open_issues_count": 80,
    "forks_count": 83
  },
  {
    "full_name": "freeCodeCamp/devdocs",
    "stargazers_count": 30719,
    "open_issues_count": 145,
    "forks_count": 2071
  },
  {
    "full_name": "henrik-ch/open-sauced-goals",
    "stargazers_count": 0,
    "open_issues_count": 6,
    "forks_count": 0
  },
  {
    "full_name": "saulpw/visidata",
    "stargazers_count": 6323,
    "open_issues_count": 83,
    "forks_count": 239
  },
  {
    "full_name": "nix-community/poetry2nix",
    "stargazers_count": 423,
    "open_issues_count": 112,
    "forks_count": 194
  },
  {
    "full_name": "open-sauced/open-sauced",
    "stargazers_count": 839,
    "open_issues_count": 9,
    "forks_count": 514
  }
]